.travis.yml
CHANGES.rst
MANIFEST.in
README.rst
setup.py
tox.ini
/home/blackwithwhite/Work/ged-soa/apps/src/thriftworker/src/cm_counter.c
/home/blackwithwhite/Work/ged-soa/apps/src/thriftworker/src/cm_heap.c
/home/blackwithwhite/Work/ged-soa/apps/src/thriftworker/src/cm_quantile.c
/home/blackwithwhite/Work/ged-soa/apps/src/thriftworker/src/cm_timer.c
/home/blackwithwhite/Work/ged-soa/apps/src/thriftworker/src/monotime.c
docs/Makefile
docs/source/api.rst
docs/source/changelog.rst
docs/source/conf.py
docs/source/index.rst
docs/source/api/modules.rst
docs/source/api/thriftworker.envs.rst
docs/source/api/thriftworker.rst
docs/source/api/thriftworker.tests.app.rst
docs/source/api/thriftworker.tests.rst
docs/source/api/thriftworker.tests.transports.rst
docs/source/api/thriftworker.tests.utilities.rst
docs/source/api/thriftworker.tests.utilities.stats.rst
docs/source/api/thriftworker.tests.workers.rst
docs/source/api/thriftworker.transports.framed.rst
docs/source/api/thriftworker.transports.rst
docs/source/api/thriftworker.utils.atomics.rst
docs/source/api/thriftworker.utils.rst
docs/source/api/thriftworker.utils.stats.rst
docs/source/api/thriftworker.workers.rst
src/cm_counter.c
src/cm_counter.h
src/cm_heap.c
src/cm_heap.h
src/cm_quantile.c
src/cm_quantile.h
src/cm_timer.c
src/cm_timer.h
src/monotime.c
thriftworker/__init__.py
thriftworker/app.py
thriftworker/constants.py
thriftworker/exceptions.py
thriftworker/listener.py
thriftworker/services.py
thriftworker/state.py
thriftworker.egg-info/PKG-INFO
thriftworker.egg-info/SOURCES.txt
thriftworker.egg-info/dependency_links.txt
thriftworker.egg-info/not-zip-safe
thriftworker.egg-info/requires.txt
thriftworker.egg-info/top_level.txt
thriftworker/hub/__init__.py
thriftworker/hub/loop.py
thriftworker/hub/queue.py
thriftworker/hub/task.py
thriftworker/hub/utils.py
thriftworker/hub/waiter.py
thriftworker/tests/__init__.py
thriftworker/tests/utils.py
thriftworker/tests/app/__init__.py
thriftworker/tests/app/test_app.py
thriftworker/tests/app/test_hub.py
thriftworker/tests/app/test_listener.py
thriftworker/tests/app/test_services.py
thriftworker/tests/app/test_state.py
thriftworker/tests/transports/__init__.py
