Metadata-Version: 1.1
Name: thriftworker
Version: 0.2.9
Summary: Process incoming request and return it's result.
Home-page: https://github.com/blackwithwhite666/thriftworker
Author: Lipin Dmitriy
Author-email: blackwithwhite666@gmail.com
License: BSD
Keywords: thrift soa
Platform: UNKNOWN
Classifier: Development Status :: 4 - Beta
Classifier: Intended Audience :: Developers
Classifier: Intended Audience :: System Administrators
Classifier: License :: OSI Approved :: BSD License
Classifier: Operating System :: POSIX
Classifier: Programming Language :: Python :: 2.7
